tensorlayer/__init__.py
tensorlayer/activation.py
tensorlayer/array_ops.py
tensorlayer/cost.py
tensorlayer/db.py
tensorlayer/distributed.py
tensorlayer/initializers.py
tensorlayer/iterate.py
tensorlayer/lazy_imports.py
tensorlayer/nlp.py
tensorlayer/package_info.py
tensorlayer/prepro.py
tensorlayer/rein.py
tensorlayer/utils.py
tensorlayer/visualize.py
tensorlayer/app/__init__.py
tensorlayer/app/computer_vision.py
tensorlayer/app/computer_vision_object_detection/__init__.py
tensorlayer/app/computer_vision_object_detection/common.py
tensorlayer/app/computer_vision_object_detection/yolov4.py
tensorlayer/app/human_pose_estimation/LCN.py
tensorlayer/app/human_pose_estimation/__init__.py
tensorlayer/app/human_pose_estimation/common.py
tensorlayer/cli/__init__.py
tensorlayer/cli/__main__.py
tensorlayer/cli/train.py
tensorlayer/decorators/__init__.py
tensorlayer/decorators/deprecated.py
tensorlayer/decorators/deprecated_alias.py
tensorlayer/decorators/method_decorator.py
tensorlayer/decorators/utils.py
tensorlayer/files/__init__.py
tensorlayer/files/utils.py
tensorlayer/files/dataset_loaders/__init__.py
tensorlayer/files/dataset_loaders/celebA_dataset.py
tensorlayer/files/dataset_loaders/cifar10_dataset.py
tensorlayer/files/dataset_loaders/cyclegan_dataset.py
tensorlayer/files/dataset_loaders/flickr_1M_dataset.py
tensorlayer/files/dataset_loaders/flickr_25k_dataset.py
tensorlayer/files/dataset_loaders/imdb_dataset.py
tensorlayer/files/dataset_loaders/matt_mahoney_dataset.py
tensorlayer/files/dataset_loaders/mnist_dataset.py
tensorlayer/files/dataset_loaders/mnist_fashion_dataset.py
tensorlayer/files/dataset_loaders/mnist_utils.py
tensorlayer/files/dataset_loaders/mpii_dataset.py
tensorlayer/files/dataset_loaders/nietzsche_dataset.py
tensorlayer/files/dataset_loaders/ptb_dataset.py
tensorlayer/files/dataset_loaders/voc_dataset.py
tensorlayer/files/dataset_loaders/wmt_en_fr_dataset.py
tensorlayer/layers/__init__.py
tensorlayer/layers/activation.py
tensorlayer/layers/core.py
tensorlayer-2.2.5.dist-info/LICENSE.rst
tensorlayer-2.2.5.dist-info/METADATA
tensorlayer-2.2.5.dist-info/WHEEL
tensorlayer-2.2.5.dist-info/top_level.txt
tensorlayer-2.2.5.dist-info/RECORD
