Metadata-Version: 2.1
Name: tensorlayer
Version: 2.2.5
Summary: High Level Tensorflow Deep Learning Library for Researcher and Engineer.
Home-page: https://github.com/tensorlayer/tensorlayer
Author: TensorLayer Contributors
Author-email: tensorlayer@gmail.com
Maintainer: TensorLayer Contributors
Maintainer-email: tensorlayer@gmail.com
License: apache
Download-URL: https://github.com/tensorlayer/tensorlayer
Keywords: deep learning,machine learning,computer vision,nlp,supervised learning,unsupervised learning,reinforcement learning,tensorflow
Platform: UNKNOWN
Classifier: Development Status :: 5 - Production/Stable
Classifier: Intended Audience :: Developers
Classifier: Intended Audience :: Science/Research
Classifier: Intended Audience :: Information Technology
Classifier: Topic :: Scientific/Engineering
Classifier: Topic :: Scientific/Engineering :: Image Recognition
Classifier: Topic :: Scientific/Engineering :: Artificial Intelligence
Classifier: Topic :: Software Development :: Libraries
Classifier: Topic :: Utilities
Classifier: License :: OSI Approved :: Apache Software License
Classifier: Programming Language :: Python :: 2
Classifier: Programming Language :: Python :: 2.7
Classifier: Programming Language :: Python :: 3
Classifier: Programming Language :: Python :: 3.5
Classifier: Programming Language :: Python :: 3.6
Classifier: Environment :: Console
Classifier: Natural Language :: English
Classifier: Operating System :: OS Independent
License-File: LICENSE.rst
Requires-Dist: imageio (>=2.5.0)
Requires-Dist: numpy (>=1.16)
Requires-Dist: progressbar2 (>=3.39.3)
Requires-Dist: requests (>=2.21.0)
Requires-Dist: scikit-learn (>=0.21.0)
Requires-Dist: scikit-image (>=0.15.0)
Requires-Dist: scipy (>=1.2.1)
Requires-Dist: wrapt (>=1.11.1)
Requires-Dist: h5py (>=2.9)
Requires-Dist: cloudpickle (>=0.8.1)
Provides-Extra: all
Requires-Dist: opencv-python (>=4.1.0.25) ; extra == 'all'
Requires-Dist: nltk (<3.5,>=3.3) ; extra == 'all'
Requires-Dist: matplotlib (<3.1,>=2.2) ; extra == 'all'
Requires-Dist: requests (>=2.21.0) ; extra == 'all'
Requires-Dist: tqdm (>=4.31.1) ; extra == 'all'
Requires-Dist: lxml (>=4.3.3) ; extra == 'all'
Requires-Dist: hyperdash (<0.16,>=0.15) ; extra == 'all'
Provides-Extra: all_cpu
Requires-Dist: opencv-python (>=4.1.0.25) ; extra == 'all_cpu'
Requires-Dist: nltk (<3.5,>=3.3) ; extra == 'all_cpu'
Requires-Dist: matplotlib (<3.1,>=2.2) ; extra == 'all_cpu'
Requires-Dist: requests (>=2.21.0) ; extra == 'all_cpu'
Requires-Dist: tqdm (>=4.31.1) ; extra == 'all_cpu'
Requires-Dist: lxml (>=4.3.3) ; extra == 'all_cpu'
Requires-Dist: hyperdash (<0.16,>=0.15) ; extra == 'all_cpu'
Requires-Dist: tensorflow (>=2.0.0-alpha0) ; extra == 'all_cpu'
Provides-Extra: all_cpu_dev
Requires-Dist: opencv-python (>=4.1.0.25) ; extra == 'all_cpu_dev'
Requires-Dist: nltk (<3.5,>=3.3) ; extra == 'all_cpu_dev'
Requires-Dist: matplotlib (<3.1,>=2.2) ; extra == 'all_cpu_dev'
Requires-Dist: requests (>=2.21.0) ; extra == 'all_cpu_dev'
Requires-Dist: tqdm (>=4.31.1) ; extra == 'all_cpu_dev'
Requires-Dist: lxml (>=4.3.3) ; extra == 'all_cpu_dev'
Requires-Dist: hyperdash (<0.16,>=0.15) ; extra == 'all_cpu_dev'
Requires-Dist: pymongo (>=3.8.0) ; extra == 'all_cpu_dev'
Requires-Dist: autopep8 (<1.5,>=1.3) ; extra == 'all_cpu_dev'
Requires-Dist: flake8-docstrings (<1.4,>=1.3) ; extra == 'all_cpu_dev'
Requires-Dist: pycodestyle (>=2.5.0) ; extra == 'all_cpu_dev'
Requires-Dist: pydocstyle (<3.1,>=2.1) ; extra == 'all_cpu_dev'
Requires-Dist: sphinx (==2.0.1) ; extra == 'all_cpu_dev'
Requires-Dist: sphinx-rtd-theme (<0.5,>=0.4) ; extra == 'all_cpu_dev'
Requires-Dist: wrapt (>=1.11.1) ; extra == 'all_cpu_dev'
Requires-Dist: h5py (>=2.9) ; extra == 'all_cpu_dev'
Requires-Dist: cloudpickle (>=0.8.1) ; extra == 'all_cpu_dev'
Requires-Dist: keras (<2.3,>=2.2) ; extra == 'all_cpu_dev'
Requires-Dist: pytest (>=4.5.0) ; extra == 'all_cpu_dev'
Requires-Dist: pytest-cache (<1.1,>=1.0) ; extra == 'all_cpu_dev'
Requires-Dist: pytest-cov (>=2.7.1) ; extra == 'all_cpu_dev'
Requires-Dist: pytest-xdist (>=1.28.0) ; extra == 'all_cpu_dev'
Requires-Dist: yapf (==0.29.0) ; extra == 'all_cpu_dev'
Requires-Dist: autoflake (==1.3.1) ; extra == 'all_cpu_dev'
Requires-Dist: isort (==4.3.21) ; extra == 'all_cpu_dev'
Requires-Dist: tensorflow (>=2.0.0-alpha0) ; extra == 'all_cpu_dev'
Provides-Extra: all_dev
Requires-Dist: opencv-python (>=4.1.0.25) ; extra == 'all_dev'
Requires-Dist: nltk (<3.5,>=3.3) ; extra == 'all_dev'
Requires-Dist: matplotlib (<3.1,>=2.2) ; extra == 'all_dev'
Requires-Dist: requests (>=2.21.0) ; extra == 'all_dev'
Requires-Dist: tqdm (>=4.31.1) ; extra == 'all_dev'
Requires-Dist: lxml (>=4.3.3) ; extra == 'all_dev'
Requires-Dist: hyperdash (<0.16,>=0.15) ; extra == 'all_dev'
Requires-Dist: pymongo (>=3.8.0) ; extra == 'all_dev'
Requires-Dist: autopep8 (<1.5,>=1.3) ; extra == 'all_dev'
Requires-Dist: flake8-docstrings (<1.4,>=1.3) ; extra == 'all_dev'
Requires-Dist: pycodestyle (>=2.5.0) ; extra == 'all_dev'
Requires-Dist: pydocstyle (<3.1,>=2.1) ; extra == 'all_dev'
Requires-Dist: sphinx (==2.0.1) ; extra == 'all_dev'
Requires-Dist: sphinx-rtd-theme (<0.5,>=0.4) ; extra == 'all_dev'
Requires-Dist: wrapt (>=1.11.1) ; extra == 'all_dev'
Requires-Dist: h5py (>=2.9) ; extra == 'all_dev'
Requires-Dist: cloudpickle (>=0.8.1) ; extra == 'all_dev'
Requires-Dist: keras (<2.3,>=2.2) ; extra == 'all_dev'
Requires-Dist: pytest (>=4.5.0) ; extra == 'all_dev'
Requires-Dist: pytest-cache (<1.1,>=1.0) ; extra == 'all_dev'
Requires-Dist: pytest-cov (>=2.7.1) ; extra == 'all_dev'
Requires-Dist: pytest-xdist (>=1.28.0) ; extra == 'all_dev'
Requires-Dist: yapf (==0.29.0) ; extra == 'all_dev'
Requires-Dist: autoflake (==1.3.1) ; extra == 'all_dev'
Requires-Dist: isort (==4.3.21) ; extra == 'all_dev'
Provides-Extra: all_gpu
Requires-Dist: opencv-python (>=4.1.0.25) ; extra == 'all_gpu'
Requires-Dist: nltk (<3.5,>=3.3) ; extra == 'all_gpu'
Requires-Dist: matplotlib (<3.1,>=2.2) ; extra == 'all_gpu'
Requires-Dist: requests (>=2.21.0) ; extra == 'all_gpu'
Requires-Dist: tqdm (>=4.31.1) ; extra == 'all_gpu'
Requires-Dist: lxml (>=4.3.3) ; extra == 'all_gpu'
Requires-Dist: hyperdash (<0.16,>=0.15) ; extra == 'all_gpu'
Requires-Dist: tensorflow-gpu (>=2.0.0-rc1) ; extra == 'all_gpu'
Provides-Extra: all_gpu_dev
Requires-Dist: opencv-python (>=4.1.0.25) ; extra == 'all_gpu_dev'
Requires-Dist: nltk (<3.5,>=3.3) ; extra == 'all_gpu_dev'
Requires-Dist: matplotlib (<3.1,>=2.2) ; extra == 'all_gpu_dev'
Requires-Dist: requests (>=2.21.0) ; extra == 'all_gpu_dev'
Requires-Dist: tqdm (>=4.31.1) ; extra == 'all_gpu_dev'
Requires-Dist: lxml (>=4.3.3) ; extra == 'all_gpu_dev'
Requires-Dist: hyperdash (<0.16,>=0.15) ; extra == 'all_gpu_dev'
Requires-Dist: pymongo (>=3.8.0) ; extra == 'all_gpu_dev'
Requires-Dist: autopep8 (<1.5,>=1.3) ; extra == 'all_gpu_dev'
Requires-Dist: flake8-docstrings (<1.4,>=1.3) ; extra == 'all_gpu_dev'
Requires-Dist: pycodestyle (>=2.5.0) ; extra == 'all_gpu_dev'
Requires-Dist: pydocstyle (<3.1,>=2.1) ; extra == 'all_gpu_dev'
Requires-Dist: sphinx (==2.0.1) ; extra == 'all_gpu_dev'
Requires-Dist: sphinx-rtd-theme (<0.5,>=0.4) ; extra == 'all_gpu_dev'
Requires-Dist: wrapt (>=1.11.1) ; extra == 'all_gpu_dev'
Requires-Dist: h5py (>=2.9) ; extra == 'all_gpu_dev'
Requires-Dist: cloudpickle (>=0.8.1) ; extra == 'all_gpu_dev'
Requires-Dist: keras (<2.3,>=2.2) ; extra == 'all_gpu_dev'
Requires-Dist: pytest (>=4.5.0) ; extra == 'all_gpu_dev'
Requires-Dist: pytest-cache (<1.1,>=1.0) ; extra == 'all_gpu_dev'
Requires-Dist: pytest-cov (>=2.7.1) ; extra == 'all_gpu_dev'
Requires-Dist: pytest-xdist (>=1.28.0) ; extra == 'all_gpu_dev'
Requires-Dist: yapf (==0.29.0) ; extra == 'all_gpu_dev'
Requires-Dist: autoflake (==1.3.1) ; extra == 'all_gpu_dev'
Requires-Dist: isort (==4.3.21) ; extra == 'all_gpu_dev'
Requires-Dist: tensorflow-gpu (>=2.0.0-rc1) ; extra == 'all_gpu_dev'
Provides-Extra: contrib_loggers
Requires-Dist: hyperdash (<0.16,>=0.15) ; extra == 'contrib_loggers'
Provides-Extra: db
Requires-Dist: pymongo (>=3.8.0) ; extra == 'db'
Provides-Extra: dev
Requires-Dist: autopep8 (<1.5,>=1.3) ; extra == 'dev'
Provides-Extra: doc
Requires-Dist: flake8-docstrings (<1.4,>=1.3) ; extra == 'doc'
Requires-Dist: pycodestyle (>=2.5.0) ; extra == 'doc'
Requires-Dist: pydocstyle (<3.1,>=2.1) ; extra == 'doc'
Requires-Dist: sphinx (==2.0.1) ; extra == 'doc'
Requires-Dist: sphinx-rtd-theme (<0.5,>=0.4) ; extra == 'doc'
Requires-Dist: wrapt (>=1.11.1) ; extra == 'doc'
Requires-Dist: h5py (>=2.9) ; extra == 'doc'
Requires-Dist: cloudpickle (>=0.8.1) ; extra == 'doc'
Provides-Extra: extra
Requires-Dist: opencv-python (>=4.1.0.25) ; extra == 'extra'
Requires-Dist: nltk (<3.5,>=3.3) ; extra == 'extra'
Requires-Dist: matplotlib (<3.1,>=2.2) ; extra == 'extra'
Requires-Dist: requests (>=2.21.0) ; extra == 'extra'
Requires-Dist: tqdm (>=4.31.1) ; extra == 'extra'
Requires-Dist: lxml (>=4.3.3) ; extra == 'extra'
Provides-Extra: test
Requires-Dist: keras (<2.3,>=2.2) ; extra == 'test'
Requires-Dist: pycodestyle (>=2.5.0) ; extra == 'test'
Requires-Dist: pydocstyle (<3.1,>=2.1) ; extra == 'test'
Requires-Dist: pytest (>=4.5.0) ; extra == 'test'
Requires-Dist: pytest-cache (<1.1,>=1.0) ; extra == 'test'
Requires-Dist: pytest-cov (>=2.7.1) ; extra == 'test'
Requires-Dist: pytest-xdist (>=1.28.0) ; extra == 'test'
Requires-Dist: sphinx (==2.0.1) ; extra == 'test'
Requires-Dist: yapf (==0.29.0) ; extra == 'test'
Requires-Dist: autoflake (==1.3.1) ; extra == 'test'
Requires-Dist: isort (==4.3.21) ; extra == 'test'
Provides-Extra: tf_cpu
Requires-Dist: tensorflow (>=2.0.0-alpha0) ; extra == 'tf_cpu'
Provides-Extra: tf_gpu
Requires-Dist: tensorflow-gpu (>=2.0.0-rc1) ; extra == 'tf_gpu'
